webpack_bundle.py
django_webpack_bundle-1.1.0.dist-info/LICENSE
django_webpack_bundle-1.1.0.dist-info/METADATA
django_webpack_bundle-1.1.0.dist-info/WHEEL
django_webpack_bundle-1.1.0.dist-info/top_level.txt
django_webpack_bundle-1.1.0.dist-info/RECORD
